cuda_kernels/__init__.py
cuda_kernels/autocorrelation/__init__.py
cuda_kernels/autocorrelation/autocorrelation.cu
cuda_kernels/reduction/__init__.py
cuda_kernels/reduction/reduction.cu
cuda_kernels-0.1.1.dist-info/licenses/LICENSE
cuda_kernels-0.1.1.dist-info/METADATA
cuda_kernels-0.1.1.dist-info/WHEEL
cuda_kernels-0.1.1.dist-info/top_level.txt
cuda_kernels-0.1.1.dist-info/RECORD
