Metadata-Version: 2.4
Name: cuda_kernels
Version: 0.1.1
Summary: CUDA accelerated correlation and sum reduction functions
Home-page: https://github.com/AstuteFern/cuda-toolkit
Author: Sukhman Virk, Shiv Mehta
Author-email: sukhmanvirk26@gmail.com
Classifier: Programming Language :: Python :: 3
Classifier: License :: OSI Approved :: MIT License
Classifier: Operating System :: OS Independent
Classifier: Topic :: Scientific/Engineering :: Mathematics
Requires-Python: >=3.6
License-File: LICENSE
Requires-Dist: numpy>=1.16.0
Provides-Extra: cuda
Requires-Dist: torch>=1.7.0; extra == "cuda"
Dynamic: author
Dynamic: author-email
Dynamic: classifier
Dynamic: description
Dynamic: description-content-type
Dynamic: home-page
Dynamic: license-file
Dynamic: provides-extra
Dynamic: requires-dist
Dynamic: requires-python
Dynamic: summary
